[
	{
		"__TYPE__": "SharedSliceContent",
		"variation": "default",
		"primary": {
			"text": {
				"__TYPE__": "StructuredTextContent",
				"value": [
					{
						"type": "paragraph",
						"content": {
							"text": "Voluptate labore duis do laboris enim exercitation minim dolore Lorem culpa."
						}
					}
				]
			},
			"backgroundImage": {
				"url": "https://images.unsplash.com/photo-1616679312958-a86d9539afae?crop=entropy&cs=srgb&fm=jpg&ixid=M3wzMzc0NjN8MHwxfHNlYXJjaHw0fHxjaXRydXMlMjBmcnVpdHxlbnwwfHx8fDE3MTk1MzAwNDZ8MA&ixlib=rb-4.0.3&q=85",
				"alt": "orange fruit on white ceramic plate",
				"origin": {
					"id": "Jr7t5QviCDM",
					"url": "https://images.unsplash.com/photo-1616679312958-a86d9539afae?crop=entropy&cs=srgb&fm=jpg&ixid=M3wzMzc0NjN8MHwxfHNlYXJjaHw0fHxjaXRydXMlMjBmcnVpdHxlbnwwfHx8fDE3MTk1MzAwNDZ8MA&ixlib=rb-4.0.3&q=85",
					"width": 3024,
					"height": 4032
				},
				"width": 3024,
				"height": 4032,
				"edit": {
					"background": "transparent",
					"zoom": 1,
					"crop": {
						"x": 0,
						"y": 0
					}
				},
				"credits": null,
				"__TYPE__": "ImageContent",
				"thumbnails": {}
			},
			"heading": {
				"__TYPE__": "StructuredTextContent",
				"value": [
					{
						"type": "heading1",
						"content": {
							"text": "Increase"
						}
					}
				]
			},
			"buttons": {
				"__TYPE__": "GroupContentType",
				"value": [
					{
						"__TYPE__": "GroupItemContent",
						"value": [
							[
								"button_link",
								{
									"__TYPE__": "LinkContent",
									"value": {
										"__TYPE__": "ExternalLink",
										"url": "http://twitter.com"
									}
								}
							],
							[
								"button_text",
								{
									"__TYPE__": "FieldContent",
									"value": "your",
									"type": "Text"
								}
							],
							[
								"button_type",
								{
									"__TYPE__": "FieldContent",
									"value": "secondary",
									"type": "Select"
								}
							]
						]
					}
				]
			}
		},
		"items": [
			{
				"__TYPE__": "GroupItemContent",
				"value": []
			}
		]
	}
]